python_steptrace-0.2.0.dist-info/licenses/LICENSE
steptrace/__init__.py
steptrace/tracer.py
python_steptrace-0.2.0.dist-info/METADATA
python_steptrace-0.2.0.dist-info/WHEEL
python_steptrace-0.2.0.dist-info/top_level.txt
python_steptrace-0.2.0.dist-info/RECORD
