Metadata-Version: 2.4
Name: python-steptrace
Version: 0.2.0
Summary: A lightweight line-by-line Python execution tracer
Author-email: Sepuh Hovhannisyan <contact@skillcheckmate.com>
License: MIT
Project-URL: Homepage, https://github.com/Sepuh077/steptrace
Project-URL: Repository, https://github.com/Sepuh077/steptrace
Keywords: debugging,tracing,python
Classifier: Programming Language :: Python :: 3
Classifier: License :: OSI Approved :: MIT License
Classifier: Operating System :: OS Independent
Requires-Python: >=3.10
License-File: LICENSE
Dynamic: license-file
